{"dice": 0.8391578793525696,"per_dataset_modality_task_dice": {"MSD_mr_42": {"CT": {},"MRI": {"prostate": 0.7490625381469727}},"T2-weighted-MRI_mr_42": {"CT": {},"MRI": {"prostate": 0.8597387075424194}},"promise12_mr_42": {"CT": {},"MRI": {"prostate": 0.888136625289917}},"SAML_mr_42": {"CT": {},"MRI": {"prostate": 0.8033840656280518}}},"per_dataset_modality_task_counts": {"MSD_mr_42": {"CT": {},"MRI": {"prostate": 6}},"T2-weighted-MRI_mr_42": {"CT": {},"MRI": {"prostate": 16}},"promise12_mr_42": {"CT": {},"MRI": {"prostate": 16}},"SAML_mr_42": {"CT": {},"MRI": {"prostate": 16}}}}